jupyterbundle/JupyterBundle.py
jupyterbundle/JupyterBundleTest.py
jupyterbundle/_config/config.yaml
jupyterbundle/_config/config_test.yaml
jupyterbundle/notebook/DataFrameDisplay.py
jupyterbundle/notebook/PandasDataFrameDisplay.py
jupyterbundle/server_detector.py
jupyterbundle/widgets/JupyterWidgets.py
jupyterbundle/widgets/JupyterWidgetsTest.py
jupyter_bundle-1.2.1.dist-info/entry_points.txt
jupyter_bundle-1.2.1.dist-info/LICENSE
jupyter_bundle-1.2.1.dist-info/WHEEL
jupyter_bundle-1.2.1.dist-info/METADATA
jupyter_bundle-1.2.1.dist-info/RECORD
